{"name":"Seleccionar productos","id":"seleccionar-productos-en-exito.com;seleccionar-productos","testSteps":[{"number":1,"description":"Dado que estoy loggeado en la pagina","duration":30839,"startTime":"2023-10-06T21:31:36.036928600-05:00[America/Bogota]","screenshots":[{"screenshot":"8c39235aa32be8f7132aeca89796d3a7ecb26e71acefdfb266342e5afc52e64a.png","timeStamp":1696645926876}],"result":"SUCCESS","precondition":false,"level":0,"children":[{"number":2,"description":"Valentina abrir pagina exito","duration":5072,"startTime":"2023-10-06T21:31:43.628970900-05:00[America/Bogota]","screenshots":[{"screenshot":"aef01e10bef36255fbfd96d5c2927a30c404516c1df6e36dee0685165fce61ad.png","timeStamp":1696645903931},{"screenshot":"dd6e660366e3e96d82ab240d5f2dc7cf3d6ddb2684a943ab27b9424d3532d5cd.png","timeStamp":1696645908701}],"result":"SUCCESS","precondition":false,"level":1,"children":[{"number":3,"description":"Valentina opens the Abrir pagina","duration":4708,"startTime":"2023-10-06T21:31:43.952152400-05:00[America/Bogota]","screenshots":[{"screenshot":"aef01e10bef36255fbfd96d5c2927a30c404516c1df6e36dee0685165fce61ad.png","timeStamp":1696645903974},{"screenshot":"dd6e660366e3e96d82ab240d5f2dc7cf3d6ddb2684a943ab27b9424d3532d5cd.png","timeStamp":1696645908660}],"result":"SUCCESS","precondition":false,"level":2}]},{"number":4,"description":"Valentina iniciar sesion","duration":17661,"startTime":"2023-10-06T21:31:48.730720900-05:00[America/Bogota]","screenshots":[{"screenshot":"545ac0710bfcf6b8d9e51653e1b091da0d24b985807a8af66473d43272701c37.png","timeStamp":1696645910271},{"screenshot":"af96ca5c47c933fe0e9eaac9933d07349a9ba2daf8372eaf849d148a1c2f87ac.png","timeStamp":1696645926392}],"result":"SUCCESS","precondition":false,"level":1,"children":[{"number":5,"description":"Valentina espera 5 segundo(s) antes de ejecutar el siguiente paso","duration":6579,"startTime":"2023-10-06T21:31:50.392276400-05:00[America/Bogota]","screenshots":[{"screenshot":"545ac0710bfcf6b8d9e51653e1b091da0d24b985807a8af66473d43272701c37.png","timeStamp":1696645911356},{"screenshot":"c172c667f5ba8a614a84d736f15bedf2d2949c50ea403ae0853bb15738e3c1b2.png","timeStamp":1696645916971}],"result":"SUCCESS","precondition":false,"level":2},{"number":6,"description":"Valentina clicks on Modal de publicidad","duration":1656,"startTime":"2023-10-06T21:31:57.252829500-05:00[America/Bogota]","screenshots":[{"screenshot":"d04ff67a0ffa81a42ed5945b31d7d264d4115e017d7ea1d7d88c6b6bec180e55.png","timeStamp":1696645917785},{"screenshot":"d38881026342c77aae0301446cb801cd98ceaa1c8fcf583a0625846d24f42a9e.png","timeStamp":1696645918909}],"result":"SUCCESS","precondition":false,"level":2},{"number":7,"description":"Valentina clicks on Mi cuenta","duration":1006,"startTime":"2023-10-06T21:31:58.911661500-05:00[America/Bogota]","screenshots":[{"screenshot":"d38881026342c77aae0301446cb801cd98ceaa1c8fcf583a0625846d24f42a9e.png","timeStamp":1696645918928},{"screenshot":"23fc921b76dd670c49f420d4a3664d49c6ef3d305740e8d4eda9aa398ef82920.png","timeStamp":1696645919917}],"result":"SUCCESS","precondition":false,"level":2},{"number":8,"description":"Valentina clicks on Opcion de ingreso","duration":1602,"startTime":"2023-10-06T21:32:00.139427800-05:00[America/Bogota]","screenshots":[{"screenshot":"660bab6098dbb2b369e6e8cff168d8df4aca9f8c9493761a97b317d76e9d39ae.png","timeStamp":1696645920692},{"screenshot":"74ab3719e6547c89bd2bb3aa1cc1e2838e0a0a88271af7a17e625fb184b1151c.png","timeStamp":1696645921742}],"result":"SUCCESS","precondition":false,"level":2},{"number":9,"description":"Valentina enters \u0027valentinamejiag@hotmail.com\u0027 into Opcion de ingreso","duration":2248,"startTime":"2023-10-06T21:32:01.745134600-05:00[America/Bogota]","screenshots":[{"screenshot":"74ab3719e6547c89bd2bb3aa1cc1e2838e0a0a88271af7a17e625fb184b1151c.png","timeStamp":1696645921769},{"screenshot":"d541c07fa8f8804fb4449ee2f8620654db39939ed3da18422c3956310ba66f69.png","timeStamp":1696645923994}],"result":"SUCCESS","precondition":false,"level":2},{"number":10,"description":"Valentina enters \u0027Valen123\u0027 into Opcion de ingreso","duration":1314,"startTime":"2023-10-06T21:32:03.996114500-05:00[America/Bogota]","screenshots":[{"screenshot":"d541c07fa8f8804fb4449ee2f8620654db39939ed3da18422c3956310ba66f69.png","timeStamp":1696645924017},{"screenshot":"c9537570350c966e95af98652db0b6bea703f165e003d59f19f71150217b09c3.png","timeStamp":1696645925310}],"result":"SUCCESS","precondition":false,"level":2},{"number":11,"description":"Valentina clicks on Opcion de ingreso","duration":1048,"startTime":"2023-10-06T21:32:05.312594300-05:00[America/Bogota]","screenshots":[{"screenshot":"c9537570350c966e95af98652db0b6bea703f165e003d59f19f71150217b09c3.png","timeStamp":1696645925337},{"screenshot":"af96ca5c47c933fe0e9eaac9933d07349a9ba2daf8372eaf849d148a1c2f87ac.png","timeStamp":1696645926360}],"result":"SUCCESS","precondition":false,"level":2}]}]},{"number":12,"description":"Cuando selecciono la categoria Tecnologia y la subcategoria Televisores","duration":10940,"startTime":"2023-10-06T21:32:06.879404500-05:00[America/Bogota]","screenshots":[{"screenshot":"c8ef0a9d34b3388cbc36eeeaa505cc716e33bbc658b9c25f6d7742da68d7345d.png","timeStamp":1696645937820}],"result":"SUCCESS","precondition":false,"level":0,"children":[{"number":13,"description":"Valentina seleccionar categoria","duration":10066,"startTime":"2023-10-06T21:32:06.932263100-05:00[America/Bogota]","screenshots":[{"screenshot":"8e414dd960b134c609f22f19d38536b1a940baf892ee7024bff3030bfc2c7050.png","timeStamp":1696645929432},{"screenshot":"c8ef0a9d34b3388cbc36eeeaa505cc716e33bbc658b9c25f6d7742da68d7345d.png","timeStamp":1696645936998}],"result":"SUCCESS","precondition":false,"level":1,"children":[{"number":14,"description":"Valentina clicks on Menu","duration":2313,"startTime":"2023-10-06T21:32:12.110415300-05:00[America/Bogota]","screenshots":[{"screenshot":"e06e24d031814929384f022a71d675927144ae7aef959141f1f31bb9ad4e11b9.png","timeStamp":1696645933175},{"screenshot":"62b2ff5b5b0548530d6b0bbd4822f0d1a69256ed5107bbb39e634ee6dd7f40c5.png","timeStamp":1696645934424}],"result":"SUCCESS","precondition":false,"level":2},{"number":15,"description":"Valentina clicks on Categoria","duration":986,"startTime":"2023-10-06T21:32:14.427098900-05:00[America/Bogota]","screenshots":[{"screenshot":"62b2ff5b5b0548530d6b0bbd4822f0d1a69256ed5107bbb39e634ee6dd7f40c5.png","timeStamp":1696645934448},{"screenshot":"1384b8ba85ef8f1b70b3904f9d8b7da5bc4770220e8cfb114c6daa8febaf8c16.png","timeStamp":1696645935413}],"result":"SUCCESS","precondition":false,"level":2},{"number":16,"description":"Valentina clicks on Subcategoria","duration":1533,"startTime":"2023-10-06T21:32:15.416656300-05:00[America/Bogota]","screenshots":[{"screenshot":"1384b8ba85ef8f1b70b3904f9d8b7da5bc4770220e8cfb114c6daa8febaf8c16.png","timeStamp":1696645935436},{"screenshot":"c8ef0a9d34b3388cbc36eeeaa505cc716e33bbc658b9c25f6d7742da68d7345d.png","timeStamp":1696645936950}],"result":"SUCCESS","precondition":false,"level":2}]}]},{"number":17,"description":"Y selecciono los televisores de forma aleatoria y agrego cantidades diferentes a cada seleccion","duration":132755,"startTime":"2023-10-06T21:32:17.823221700-05:00[America/Bogota]","screenshots":[{"screenshot":"f0825385ca4cde8bb23db678554bd9107994975a0ede407dd410947ac179925c.png","timeStamp":1696646070578}],"result":"SUCCESS","precondition":false,"level":0,"children":[{"number":18,"description":"Valentina seleccionar televisor aleatorio","duration":132699,"startTime":"2023-10-06T21:32:17.863115400-05:00[America/Bogota]","screenshots":[{"screenshot":"38d08aed194d8a0ce0bc7a378209bf70e7d44f91d28f589b54997ea06ad4fc04.png","timeStamp":1696645939295},{"screenshot":"f0825385ca4cde8bb23db678554bd9107994975a0ede407dd410947ac179925c.png","timeStamp":1696646070562}],"result":"SUCCESS","precondition":false,"level":1,"children":[{"number":19,"description":"Valentina espera 5 segundo(s) antes de ejecutar el siguiente paso","duration":6375,"startTime":"2023-10-06T21:32:22.566537200-05:00[America/Bogota]","screenshots":[{"screenshot":"80535f7015110703ba23c24d209110dfcc21e6113079adb2accd78548d6055d3.png","timeStamp":1696645943287},{"screenshot":"80a20f69d7474e5e32f7b5397e979080e4485d570ed772f1063b803a2e0182cc.png","timeStamp":1696645948941}],"result":"SUCCESS","precondition":false,"level":2},{"number":20,"description":"Valentina clicks on Botón comprar","duration":4197,"startTime":"2023-10-06T21:32:29.343435400-05:00[America/Bogota]","screenshots":[{"screenshot":"8179f776d31b1a89759438bf6c9f4a87956bb01c53b05e5de1658fdf947abe70.png","timeStamp":1696645949927},{"screenshot":"1694bf50fdc44999fcd6b1ca338657dd016c55c176454a48386d4ec68089b511.png","timeStamp":1696645953541}],"result":"SUCCESS","precondition":false,"level":2},{"number":21,"description":"Valentina clicks on Botón cantidad","duration":4343,"startTime":"2023-10-06T21:32:33.778587-05:00[America/Bogota]","screenshots":[{"screenshot":"85ba09afbf355e5ce238bfe516b5f91f73bd390d125af8d8e2d8607e3ea9092b.png","timeStamp":1696645954219},{"screenshot":"03fa9799878bfa51dae953eb678d284c069654b9e9f1929d22760d14d46a4605.png","timeStamp":1696645958120}],"result":"SUCCESS","precondition":false,"level":2},{"number":22,"description":"Valentina espera 5 segundo(s) antes de ejecutar el siguiente paso","duration":6122,"startTime":"2023-10-06T21:32:38.133952900-05:00[America/Bogota]","screenshots":[{"screenshot":"d0e13491fe5c39da57df3b4836d980d9c11bb4be7744a35b96aabd60614c2142.png","timeStamp":1696645958757},{"screenshot":"7fbfd2bd141fc2acab74dc25aba820126995f54fa5b047997be95343cc9aae0f.png","timeStamp":1696645964255}],"result":"SUCCESS","precondition":false,"level":2},{"number":23,"description":"Valentina espera 5 segundo(s) antes de ejecutar el siguiente paso","duration":5914,"startTime":"2023-10-06T21:32:44.726867800-05:00[America/Bogota]","screenshots":[{"screenshot":"6d0e7835c79060a8216670c1e5772a6531581ed3e6984d25eecf58c0459134d8.png","timeStamp":1696645965177},{"screenshot":"10bffcb901e448cc79885e25da013254d875d4acb0f4658af35dae28c72c333c.png","timeStamp":1696645970640}],"result":"SUCCESS","precondition":false,"level":2},{"number":24,"description":"Valentina clicks on Botón comprar","duration":2257,"startTime":"2023-10-06T21:32:50.827474200-05:00[America/Bogota]","screenshots":[{"screenshot":"814d3b719090e78cc042d4f5c95a590b447b11fe066641f5ce6489f2d5aa8c39.png","timeStamp":1696645971273},{"screenshot":"8888ff002c8e3a5f2447fac0a9a7d5fa8448426882103abcb0591049ba3cc5d8.png","timeStamp":1696645973084}],"result":"SUCCESS","precondition":false,"level":2},{"number":25,"description":"Valentina clicks on Botón cantidad","duration":1931,"startTime":"2023-10-06T21:32:53.300081-05:00[America/Bogota]","screenshots":[{"screenshot":"6c1af05ef59b6697e949eaf4567bf81644dbbfd4181d1eac81e772f2859dd153.png","timeStamp":1696645973788},{"screenshot":"93e418c5c9d50e220ca03d0f9596d8507f5b0a28fa59f2c359856f26a4f29063.png","timeStamp":1696645975231}],"result":"SUCCESS","precondition":false,"level":2},{"number":26,"description":"Valentina espera 5 segundo(s) antes de ejecutar el siguiente paso","duration":5547,"startTime":"2023-10-06T21:32:55.232523300-05:00[America/Bogota]","screenshots":[{"screenshot":"93e418c5c9d50e220ca03d0f9596d8507f5b0a28fa59f2c359856f26a4f29063.png","timeStamp":1696645975248},{"screenshot":"648d853c3e6a5a055ceeb3173e6c29781384f9aee97d7dca55237c5640468e0e.png","timeStamp":1696645980780}],"result":"SUCCESS","precondition":false,"level":2},{"number":27,"description":"Valentina espera 5 segundo(s) antes de ejecutar el siguiente paso","duration":5981,"startTime":"2023-10-06T21:33:00.980774500-05:00[America/Bogota]","screenshots":[{"screenshot":"bc88590a1dad7e0cf4aaf9a0d34176702453b0db459447a2fd9f30face941cc5.png","timeStamp":1696645981470},{"screenshot":"ab685435df4dc810e2392b51efa1e1ae171c3df180a17af3ce6482b99367940e.png","timeStamp":1696645986961}],"result":"SUCCESS","precondition":false,"level":2},{"number":28,"description":"Valentina clicks on Botón comprar","duration":2714,"startTime":"2023-10-06T21:33:07.220301500-05:00[America/Bogota]","screenshots":[{"screenshot":"fde535e2b270899e2ffbb340cd2be407d79e44d0f33735914e7b0828ec9ab342.png","timeStamp":1696645987702},{"screenshot":"68c982858b83adbfd2949d202b31aa9eebabd721180af1ec512ed22c16fddb7e.png","timeStamp":1696645989935}],"result":"SUCCESS","precondition":false,"level":2},{"number":29,"description":"Valentina clicks on Botón cantidad","duration":2172,"startTime":"2023-10-06T21:33:10.231803100-05:00[America/Bogota]","screenshots":[{"screenshot":"beab5cbe1bd4223e30f57723e2aca4dc8d5aac013c9a752f4a77ee85aba823c8.png","timeStamp":1696645990757},{"screenshot":"0ebfc2c1a73b01e683d53f2b44b1288ea44de6fb8469afb0616788a4514f23ff.png","timeStamp":1696645992403}],"result":"SUCCESS","precondition":false,"level":2},{"number":30,"description":"Valentina espera 5 segundo(s) antes de ejecutar el siguiente paso","duration":5478,"startTime":"2023-10-06T21:33:12.405974100-05:00[America/Bogota]","screenshots":[{"screenshot":"0ebfc2c1a73b01e683d53f2b44b1288ea44de6fb8469afb0616788a4514f23ff.png","timeStamp":1696645992423},{"screenshot":"7dfb9f3d2355b42fc871db7c340d8a283a6fa87c83a60b883ffb6e0ec33aba87.png","timeStamp":1696645997884}],"result":"SUCCESS","precondition":false,"level":2},{"number":31,"description":"Valentina clicks on Botón cantidad","duration":1862,"startTime":"2023-10-06T21:33:18.116300300-05:00[America/Bogota]","screenshots":[{"screenshot":"1ed106ba53fde2d7fc92adf94d7523b8226e3dce1e74b8be9da4e1771b08ff43.png","timeStamp":1696645998607},{"screenshot":"9967470a70ee91ff860ce9a85d22f30fbadebbea0a35cdb241f99ee06fed1c6d.png","timeStamp":1696645999978}],"result":"SUCCESS","precondition":false,"level":2},{"number":32,"description":"Valentina espera 5 segundo(s) antes de ejecutar el siguiente paso","duration":5442,"startTime":"2023-10-06T21:33:19.980924500-05:00[America/Bogota]","screenshots":[{"screenshot":"9967470a70ee91ff860ce9a85d22f30fbadebbea0a35cdb241f99ee06fed1c6d.png","timeStamp":1696646000001},{"screenshot":"95ba256f0c8a3ed28d3bd7ab158c97238bda879498545e44c6d31354d1639768.png","timeStamp":1696646005423}],"result":"SUCCESS","precondition":false,"level":2},{"number":33,"description":"Valentina clicks on Botón cantidad","duration":1971,"startTime":"2023-10-06T21:33:25.629943600-05:00[America/Bogota]","screenshots":[{"screenshot":"4c54d175d322064baba935d1ddbf7d3c0c6b9988e0a613e673f3199f4caff47e.png","timeStamp":1696646006074},{"screenshot":"d67ed0137ace173addb777e3b7db7a0bfffbb006bacc0b40e86ed9f7d2f44aab.png","timeStamp":1696646007601}],"result":"SUCCESS","precondition":false,"level":2},{"number":34,"description":"Valentina espera 5 segundo(s) antes de ejecutar el siguiente paso","duration":5479,"startTime":"2023-10-06T21:33:27.603673100-05:00[America/Bogota]","screenshots":[{"screenshot":"d67ed0137ace173addb777e3b7db7a0bfffbb006bacc0b40e86ed9f7d2f44aab.png","timeStamp":1696646007627},{"screenshot":"46b277c4cc0c50c03f8c315726a3c7d6127415fd39b8854a4100bf78d007ca48.png","timeStamp":1696646013083}],"result":"SUCCESS","precondition":false,"level":2},{"number":35,"description":"Valentina espera 5 segundo(s) antes de ejecutar el siguiente paso","duration":5923,"startTime":"2023-10-06T21:33:33.231668200-05:00[America/Bogota]","screenshots":[{"screenshot":"d8f825f8ba73e13b4a41a1a781636e0cbe91c34254d0e56607957611ccb2d07f.png","timeStamp":1696646013679},{"screenshot":"b52b7f905fb7271a59341e32a337bc915c2f5183e205a1734e41eddacaf76e60.png","timeStamp":1696646019155}],"result":"SUCCESS","precondition":false,"level":2},{"number":36,"description":"Valentina clicks on Botón comprar","duration":2382,"startTime":"2023-10-06T21:33:39.365666900-05:00[America/Bogota]","screenshots":[{"screenshot":"ce71000bec3bb05efb55c9a10bd6a0b2f0b9f002d0d7f5d2770afd88fcf636ae.png","timeStamp":1696646019809},{"screenshot":"906b6552db86cbd22f86bac77f02e72bef8ea49784c20a3ba7e6304108357688.png","timeStamp":1696646021747}],"result":"SUCCESS","precondition":false,"level":2},{"number":37,"description":"Valentina clicks on Botón cantidad","duration":1981,"startTime":"2023-10-06T21:33:41.964651700-05:00[America/Bogota]","screenshots":[{"screenshot":"8b2ad61ed0c7979dbabfe2c10616c148318a17570aac55c907c4fe83109e434d.png","timeStamp":1696646022404},{"screenshot":"1e8e115368ca15dcc66010010886b0db44ec9abde096ad61560fdf260a5dbf03.png","timeStamp":1696646023946}],"result":"SUCCESS","precondition":false,"level":2},{"number":38,"description":"Valentina espera 5 segundo(s) antes de ejecutar el siguiente paso","duration":5461,"startTime":"2023-10-06T21:33:43.949501500-05:00[America/Bogota]","screenshots":[{"screenshot":"1e8e115368ca15dcc66010010886b0db44ec9abde096ad61560fdf260a5dbf03.png","timeStamp":1696646023968},{"screenshot":"7bbe4bfef339bc762c41f6a592a945d7b395f7583ea225162ecac8cc149f4116.png","timeStamp":1696646029411}],"result":"SUCCESS","precondition":false,"level":2},{"number":39,"description":"Valentina clicks on Botón cantidad","duration":2200,"startTime":"2023-10-06T21:33:49.619798100-05:00[America/Bogota]","screenshots":[{"screenshot":"292b2ef73536fa5a63f694dc5f8eb8d9fb15a03aa082118262afccc47b8b381c.png","timeStamp":1696646030152},{"screenshot":"bdadf46137de94833a88ba972646a7e49d106640d2e04b1cb1cc5aa3af118831.png","timeStamp":1696646031819}],"result":"SUCCESS","precondition":false,"level":2},{"number":40,"description":"Valentina espera 5 segundo(s) antes de ejecutar el siguiente paso","duration":5474,"startTime":"2023-10-06T21:33:51.820909800-05:00[America/Bogota]","screenshots":[{"screenshot":"bdadf46137de94833a88ba972646a7e49d106640d2e04b1cb1cc5aa3af118831.png","timeStamp":1696646031838},{"screenshot":"39a455f96f04c4f7e7d6252132bb7b939f6bf7199e2271ce9e83e1cd97596454.png","timeStamp":1696646037295}],"result":"SUCCESS","precondition":false,"level":2},{"number":41,"description":"Valentina clicks on Botón cantidad","duration":1832,"startTime":"2023-10-06T21:33:57.478579100-05:00[America/Bogota]","screenshots":[{"screenshot":"9d109cf893caff04cf1e8d9c31d435ea140f8b9db6eaaff341b0b1d823bcebbb.png","timeStamp":1696646037909},{"screenshot":"3707716368d80162172035d792c4b33b817c197f964848779ae7e3c9477f92bb.png","timeStamp":1696646039310}],"result":"SUCCESS","precondition":false,"level":2},{"number":42,"description":"Valentina espera 5 segundo(s) antes de ejecutar el siguiente paso","duration":5461,"startTime":"2023-10-06T21:33:59.312825200-05:00[America/Bogota]","screenshots":[{"screenshot":"3707716368d80162172035d792c4b33b817c197f964848779ae7e3c9477f92bb.png","timeStamp":1696646039342},{"screenshot":"ac1168fa7ff9cfe826f0238b77f4427cc255108944f824894b4b97b07bf0ad9b.png","timeStamp":1696646044774}],"result":"SUCCESS","precondition":false,"level":2},{"number":43,"description":"Valentina espera 5 segundo(s) antes de ejecutar el siguiente paso","duration":5975,"startTime":"2023-10-06T21:34:04.917498500-05:00[America/Bogota]","screenshots":[{"screenshot":"5d7ec1af795538eec39cce161b244bcb3c7ae64c7cbe57fe1f8e8b6665539a9c.png","timeStamp":1696646045404},{"screenshot":"d079c4db738ee2414b3940f427a6e85af4f553b89e625e4c15dba177a8cfe7d6.png","timeStamp":1696646050892}],"result":"SUCCESS","precondition":false,"level":2},{"number":44,"description":"Valentina clicks on Botón comprar","duration":3083,"startTime":"2023-10-06T21:34:11.115965400-05:00[America/Bogota]","screenshots":[{"screenshot":"d8f12e97282f95e3f3befa3901e048d49ba3b234c067b77eb8f7933e10562768.png","timeStamp":1696646051614},{"screenshot":"9dcbba869eca46152d2e8ddc8655168366ac6b05021c4036fc09776f85692e9f.png","timeStamp":1696646054199}],"result":"SUCCESS","precondition":false,"level":2},{"number":45,"description":"Valentina clicks on Botón cantidad","duration":2232,"startTime":"2023-10-06T21:34:14.617006800-05:00[America/Bogota]","screenshots":[{"screenshot":"1c72ce505aec38dc8709c999a7aaeb14c074eab086c54ba1dc2e6754a1da0caf.png","timeStamp":1696646055093},{"screenshot":"36d65a2d6d91ab31ed560c3ce7c0975f06e414b40964fa936608868dc6a3ad4b.png","timeStamp":1696646056848}],"result":"SUCCESS","precondition":false,"level":2},{"number":46,"description":"Valentina espera 5 segundo(s) antes de ejecutar el siguiente paso","duration":5478,"startTime":"2023-10-06T21:34:16.850667500-05:00[America/Bogota]","screenshots":[{"screenshot":"36d65a2d6d91ab31ed560c3ce7c0975f06e414b40964fa936608868dc6a3ad4b.png","timeStamp":1696646056876},{"screenshot":"45bbca93077d3aa11bc1fc8b50a349b568b7fc19b5c78c5d32b060e54b2030fc.png","timeStamp":1696646062327}],"result":"SUCCESS","precondition":false,"level":2},{"number":47,"description":"Valentina clicks on Botón cantidad","duration":1958,"startTime":"2023-10-06T21:34:22.569261700-05:00[America/Bogota]","screenshots":[{"screenshot":"d04947bd7d60848f8848b5d2546521dcb40824ed28bcda85d62651b9f43790c6.png","timeStamp":1696646062990},{"screenshot":"9c33f2d3775b22912c49744ddae0937274eee71126c52383f15fe6a274b7051d.png","timeStamp":1696646064527}],"result":"SUCCESS","precondition":false,"level":2},{"number":48,"description":"Valentina espera 5 segundo(s) antes de ejecutar el siguiente paso","duration":5440,"startTime":"2023-10-06T21:34:24.530713300-05:00[America/Bogota]","screenshots":[{"screenshot":"9c33f2d3775b22912c49744ddae0937274eee71126c52383f15fe6a274b7051d.png","timeStamp":1696646064545},{"screenshot":"677a9826cc646a6c36b054dd26d31526b3bfc1f87a19331fc3378cf6bd5fe577.png","timeStamp":1696646069970}],"result":"SUCCESS","precondition":false,"level":2}]}]},{"number":49,"description":"Entonces Deberia visualizar los nombres precios cantidades y numero de productos","duration":24,"startTime":"2023-10-06T21:34:30.579286500-05:00[America/Bogota]","screenshots":[{"screenshot":"f0825385ca4cde8bb23db678554bd9107994975a0ede407dd410947ac179925c.png","timeStamp":1696646070604}],"result":"SUCCESS","precondition":false,"level":0}],"userStory":{"id":"seleccionar-productos-en-exito.com","storyName":"Seleccionar productos en exito.com","path":"front/Productos.feature","narrative":"  yo como usuario de la pagina exito.com\n  quiero seleccionar cinco productos por distintas cantidades","type":"feature"},"featureTag":{"name":"Front/Seleccionar productos en exito.com","type":"feature","displayName":"Front/Seleccionar productos en exito.com"},"title":"Seleccionar productos","description":"","backgroundTitle":"","backgroundDescription":"","tags":[{"name":"Front/Seleccionar productos en exito.com","type":"feature","displayName":"Seleccionar productos en exito.com"},{"name":"Front","type":"capability","displayName":"Front"}],"startTime":"2023-10-06T21:31:35.621039700-05:00[America/Bogota]","duration":174988,"projectKey":"","sessionId":"f47cbb9387a44bc6a98d61fa2bb3d567","driver":"chrome","isManualTestingUpToDate":false,"manual":false,"testSource":"Cucumber","actors":[{"name":"Valentina","can":["call an API at https://dummy.restapiexample.com/","browse the web"]}],"result":"SUCCESS"}